MANIFEST.in
README.rst
setup.py
nemo_arethusa_plugin/__init__.py
nemo_arethusa_plugin.egg-info/PKG-INFO
nemo_arethusa_plugin.egg-info/SOURCES.txt
nemo_arethusa_plugin.egg-info/dependency_links.txt
nemo_arethusa_plugin.egg-info/not-zip-safe
nemo_arethusa_plugin.egg-info/requires.txt
nemo_arethusa_plugin.egg-info/top_level.txt
nemo_arethusa_plugin/data/assets/css/.fontcustom-data
nemo_arethusa_plugin/data/assets/css/arethusa.min.css
nemo_arethusa_plugin/data/assets/css/colorpicker.css
nemo_arethusa_plugin/data/assets/css/font-awesome.min.css
nemo_arethusa_plugin/data/assets/css/foundation-icons.css
nemo_arethusa_plugin/data/assets/css/foundation-icons.eot
nemo_arethusa_plugin/data/assets/css/foundation-icons.svg
nemo_arethusa_plugin/data/assets/css/foundation-icons.ttf
nemo_arethusa_plugin/data/assets/css/foundation-icons.woff
nemo_arethusa_plugin/data/assets/fonts/FontAwesome.otf
nemo_arethusa_plugin/data/assets/fonts/fontawesome-webfont.eot
nemo_arethusa_plugin/data/assets/fonts/fontawesome-webfont.svg
nemo_arethusa_plugin/data/assets/fonts/fontawesome-webfont.ttf
nemo_arethusa_plugin/data/assets/fonts/fontawesome-webfont.woff
nemo_arethusa_plugin/data/assets/i18n/bg.json
nemo_arethusa_plugin/data/assets/i18n/de.json
nemo_arethusa_plugin/data/assets/i18n/en.json
nemo_arethusa_plugin/data/assets/i18n/fr.json
nemo_arethusa_plugin/data/assets/i18n/hr.json
nemo_arethusa_plugin/data/assets/i18n/it.json
nemo_arethusa_plugin/data/assets/i18n/ka.json
nemo_arethusa_plugin/data/assets/i18n/pt_BR.json
nemo_arethusa_plugin/data/assets/js/arethusa.min.js
nemo_arethusa_plugin/data/assets/js/arethusa.packages.min.js
nemo_arethusa_plugin/data/assets/js/arethusa.widget.loader.js
nemo_arethusa_plugin/data/assets/js/dist/README.md
nemo_arethusa_plugin/data/assets/js/dist/arethusa.artificial_token.concat.js
nemo_arethusa_plugin/data/assets/js/dist/arethusa.artificial_token.min.js
nemo_arethusa_plugin/data/assets/js/dist/arethusa.artificial_token.min.map
nemo_arethusa_plugin/data/assets/js/dist/arethusa.comments.concat.js
nemo_arethusa_plugin/data/assets/js/dist/arethusa.comments.min.js
nemo_arethusa_plugin/data/assets/js/dist/arethusa.comments.min.map
nemo_arethusa_plugin/data/assets/js/dist/arethusa.concat.js
