Metadata-Version: 1.0
Name: nemo-arethusa-plugin
Version: 0.0.1
Summary: Plugin for Capitains Nemo to load Arethusa on passage page
Home-page: https://github.com/alpheios/nemo_arethusa_plugin
Author: Thibault Clerice
Author-email: leponteineptique@gmail.com
License: GNU GPL
Platform: UNKNOWN
